__init__.py
mcp4hal/__init__.py
mcp4hal/core/__init__.py
mcp4hal/core/protocol/__init__.py
mcp4hal/core/protocol/mqtt_const.py
mcp4hal/core/protocol/mqtt_schema.py
mcp4hal/hal/__init__.py
mcp4hal/hal/mqtt/__init__.py
mcp4hal/hal/mqtt/mcp_server_proxy_mqtt_supervisor.py
mcp4hal/hal/mqtt/mcp_server_proxy_mqtt_worker.py
mcp4hal/hal/mqtt/mqtt_client.py
mcp4hal/hub/__init__.py
mcp4hal/hub/registry.py
mcp4hal/utils/__init__.py
mcp4hal/utils/logger.py
mcp4hal-0.0.10.dist-info/METADATA
mcp4hal-0.0.10.dist-info/WHEEL
mcp4hal-0.0.10.dist-info/top_level.txt
mcp4hal-0.0.10.dist-info/RECORD
