Metadata-Version: 2.4
Name: mcp4hal
Version: 0.0.10
Summary: MCP(Model Context Protocol) Hardware Abstract Layer
Author-email: Jinsong Li <manson.li3307@gmail.com>
Requires-Python: >=3.10
Requires-Dist: python-dotenv
Requires-Dist: fastapi
Requires-Dist: uvicorn
Requires-Dist: mcp
Requires-Dist: langchain-mcp-adapters
Requires-Dist: pydantic
Requires-Dist: paho-mqtt
Requires-Dist: mcp-adapter
Requires-Dist: fastmcp
Requires-Dist: rich
Requires-Dist: strenum>=0.4.15
